drawscape_factorio/__init__.py
drawscape_factorio/create.py
drawscape_factorio/import_data.py
drawscape_factorio/main.py
drawscape_factorio/optimize.py
drawscape_factorio/theme_helper.py
drawscape_factorio/themes/__init__.py
drawscape_factorio/themes/parent.py
drawscape_factorio/themes/squares.py
drawscape_factorio/themes/squares_highres.py
drawscape_factorio-0.15.22.dist-info/LICENSE
drawscape_factorio-0.15.22.dist-info/METADATA
drawscape_factorio-0.15.22.dist-info/WHEEL
drawscape_factorio-0.15.22.dist-info/entry_points.txt
drawscape_factorio-0.15.22.dist-info/top_level.txt
drawscape_factorio-0.15.22.dist-info/RECORD
