Metadata-Version: 2.1
Name: drawscape-factorio
Version: 0.15.22
Summary: Drawscape Factorio
Home-page: https://github.com/drawscape-labs/drawscape-factorio
License-File: LICENSE
Requires-Dist: svgwrite
Requires-Dist: argparse
